fastapi_sio_di/__init__.py
fastapi_sio_di/async_admin.py
fastapi_sio_di/async_server.py
fastapi_sio_di/dependencies.py
fastapi_sio_di/params.py
fastapi_sio_di/utils.py
fastapi_sio_di-0.3.10.dist-info/licenses/LICENSE
fastapi_sio_di-0.3.10.dist-info/METADATA
fastapi_sio_di-0.3.10.dist-info/WHEEL
fastapi_sio_di-0.3.10.dist-info/top_level.txt
fastapi_sio_di-0.3.10.dist-info/RECORD
