Metadata-Version: 2.4
Name: fastapi-sio-di
Version: 0.3.10
Summary: FastAPI-SIO-DI is a library tailored for integrating Socket.IO with FastAPI. It allows you to develop real-time WebSocket applications using the familiar FastAPI style (Dependency Injection, Pydantic models).
Requires-Python: >=3.10
License-File: LICENSE
Requires-Dist: python-socketio>=5.16.0
Dynamic: license-file
